cloudformation_helper/__init__.py
cloudformation_helper/cli.py
cloudformation_helper/commands/__init__.py
cloudformation_helper/commands/deploy.py
cloudformation_helper/commands/info.py
cloudformation_helper/utils/__init__.py
cloudformation_helper/utils/aws.py
cloudformation_helper/utils/config.py
cloudformation_helper/utils/formatter.py
cloudformation_helper-0.3.1.dist-info/AUTHORS.rst
cloudformation_helper-0.3.1.dist-info/LICENSE
cloudformation_helper-0.3.1.dist-info/METADATA
cloudformation_helper-0.3.1.dist-info/WHEEL
cloudformation_helper-0.3.1.dist-info/entry_points.txt
cloudformation_helper-0.3.1.dist-info/top_level.txt
cloudformation_helper-0.3.1.dist-info/RECORD
