Metadata-Version: 2.1
Name: cloudformation-helper
Version: 0.3.1
Summary: Small python tool to make it easier to use cloudformation.
Home-page: https://github.com/calestar/cloudformation_helper
Author: Jean-Sebastien Gelinas
Author-email: calestar@gmail.com
License: MIT license
Keywords: cloudformation_helper
Platform: UNKNOWN
Classifier: Development Status :: 2 - Pre-Alpha
Classifier: Intended Audience :: Developers
Classifier: License :: OSI Approved :: MIT License
Classifier: Natural Language :: English
Classifier: Programming Language :: Python :: 3
Classifier: Programming Language :: Python :: 3.7
Classifier: Programming Language :: Python :: 3.8
Classifier: Programming Language :: Python :: 3.9
Requires-Python: >=3.7
Requires-Dist: Click (>=7.0)
Requires-Dist: boto3 (>=1.17)
Requires-Dist: PyYAML (>=5.4.1)
